spark_emr/__init__.py
spark_emr/__main__.py
spark_emr/bootstrap.py
spark_emr/const.py
spark_emr/manager.py
spark_emr/spot.py
spark_emr/step.py
spark_emr/util.py
test/__init__.py
test/config.yaml
test/test_bootstrap.py
test/test_main.py
test/test_manager.py
test/test_spot.py
test/test_step.py
test/test_util.py
test/dummy/main.py
test/dummy/setup.py
spark_emr-0.1.2.dist-info/LICENSE
spark_emr-0.1.2.dist-info/METADATA
spark_emr-0.1.2.dist-info/WHEEL
spark_emr-0.1.2.dist-info/entry_points.txt
spark_emr-0.1.2.dist-info/top_level.txt
spark_emr-0.1.2.dist-info/zip-safe
spark_emr-0.1.2.dist-info/RECORD
