Metadata-Version: 2.1
Name: spark-emr
Version: 0.1.2
Summary: Run python packages on AWS EMR
Home-page: https://www.github.com/delijati/spark-emr
Author: Josip Delic
Author-email: delijati@gmx.net
License: MIT
Keywords: AWS EMR SPARK PYSPARK
Platform: UNKNOWN
Classifier: Development Status :: 4 - Beta
Classifier: Environment :: Console
Classifier: Intended Audience :: Developers
Classifier: License :: OSI Approved :: MIT License
Classifier: Natural Language :: English
Classifier: Programming Language :: Python :: 3
Classifier: Programming Language :: Python :: 3.5
Classifier: Programming Language :: Python :: 3.6
Requires-Dist: boto3
Requires-Dist: loguru
Requires-Dist: pyyaml
Requires-Dist: spark-optimizer
Requires-Dist: pluggy (>=0.7)
